scappamento/__about__.py
scappamento/__init__.py
scappamento/__main__.py
scappamento/daddario.py
scappamento/fender.py
scappamento/frenexport.py
scappamento/hoshino.py
scappamento/mepa.py
scappamento/mogar.py
scappamento/musicpool.py
scappamento/proel.py
scappamento/suonostore.py
scappamento/supplier.py
scappamento/yamaha.py
scappamento-0.4b3.dist-info/LICENSE
scappamento-0.4b3.dist-info/METADATA
scappamento-0.4b3.dist-info/WHEEL
scappamento-0.4b3.dist-info/entry_points.txt
scappamento-0.4b3.dist-info/top_level.txt
scappamento-0.4b3.dist-info/RECORD
