Metadata-Version: 2.1
Name: scappamento
Version: 0.4b3
Summary: B2B automation for music stores
Home-page: https://github.com/lorenzobunino/scappamento
Author: Lorenzo Bunino
Author-email: bunino.lorenzo@gmail.com
License: UNKNOWN
Platform: UNKNOWN
Classifier: Programming Language :: Python :: 3
Classifier: License :: OSI Approved :: MIT License
Classifier: Operating System :: Microsoft :: Windows
Requires-Python: >=3.6
Requires-Dist: pandas (>=1.1.2)
Requires-Dist: xlrd (>=2.0.1)
Requires-Dist: xlutils (>=2.0.0)
Requires-Dist: requests (~=2.24.0)
Requires-Dist: selenium (~=3.141.0)
Requires-Dist: beautifulsoup4 (~=4.9.3)
Requires-Dist: mysql-connector-python (~=8.0.11)
Requires-Dist: chromedriver-autoinstaller (>=0.2.2)
Requires-Dist: xlwt (>=1.3.0)
Requires-Dist: olefile (>=0.46)
